bears/Constants.py
bears/VERSION
bears/__init__.py
bears/Ocaml/CommentFormatBear.py
bears/Ocaml/CommentLengthBear.py
bears/Ocaml/DependencyBear.py
bears/Ocaml/OcamlLintBear.py
bears/Ocaml/RemoveComments.py
bears/Ocaml/StringRepBear.py
bears/Ocaml/TokenBear.py
bears/Ocaml/TokenOcamlBear.py
bears/Ocaml/__init__.py
bears/apertium/ApertiumLintBear.py
bears/apertium/__init__.py
bears/c_languages/ArtisticStyleBear.py
bears/c_languages/CPPCheckBear.py
bears/c_languages/CPPCleanBear.py
bears/c_languages/CPPLintBear.py
bears/c_languages/CSecurityBear.py
bears/c_languages/CSharpLintBear.py
bears/c_languages/ClangBear.py
bears/c_languages/ClangComplexityBear.py
bears/c_languages/GNUIndentBear.py
bears/c_languages/__init__.py
bears/c_languages/codeclone_detection/ClangASTPrintBear.py
bears/c_languages/codeclone_detection/ClangCloneDetectionBear.py
bears/c_languages/codeclone_detection/ClangCountVectorCreator.py
bears/c_languages/codeclone_detection/ClangCountingConditions.py
bears/c_languages/codeclone_detection/ClangFunctionDifferenceBear.py
bears/c_languages/codeclone_detection/CloneDetectionRoutines.py
bears/c_languages/codeclone_detection/CountVector.py
bears/c_languages/codeclone_detection/__init__.py
bears/cmake/CMakeLintBear.py
bears/cmake/__init__.py
bears/coffee_script/CoffeeLintBear.py
bears/coffee_script/__init__.py
bears/configfiles/DockerfileLintBear.py
bears/configfiles/PuppetLintBear.py
bears/configfiles/TOMLBear.py
bears/configfiles/__init__.py
bears/css/CSSAutoPrefixBear.py
bears/css/CSSCombBear.py
bears/css/CSSLintBear.py
bears/css/StyleLintBear.py
bears/css/__init__.py
bears/csv/CSVLintBear.py
bears/csv/__init__.py
bears/csv/__pycache__/__init__.cpython-39.pyc
bears/dart/DartLintBear.py
bears/dart/__init__.py
bears/documentation/DocGrammarBear.py
bears/documentation/DocumentationStyleBear.py
bears/documentation/__init__.py
bears/elm/ElmLintBear.py
bears/elm/__init__.py
bears/general/AnnotationBear.py
bears/general/CPDBear.py
vyd_coala_bears-0.12.0.dev99999999999999.dist-info/LICENSE
vyd_coala_bears-0.12.0.dev99999999999999.dist-info/METADATA
vyd_coala_bears-0.12.0.dev99999999999999.dist-info/WHEEL
vyd_coala_bears-0.12.0.dev99999999999999.dist-info/dependency_links.txt
vyd_coala_bears-0.12.0.dev99999999999999.dist-info/entry_points.txt
vyd_coala_bears-0.12.0.dev99999999999999.dist-info/top_level.txt
vyd_coala_bears-0.12.0.dev99999999999999.dist-info/RECORD
