Metadata-Version: 2.1
Name: vyd-coala-bears
Version: 0.12.0.dev99999999999999
Summary: Bears for coala (Code Analysis Application)
Home-page: https://github.com/Yashashwee/coala-bears-project
Author: VYD
Author-email: avatsal38@gmail.com
Maintainer: vyd
Maintainer-email: lasse.schuirmann@gmail.com, fabian@neuschmidt.de, makman@alice.de
License: AGPL-3.0
Keywords: code-analysis,lint
Platform: any
Classifier: Development Status :: 4 - Beta
Classifier: Environment :: Plugins
Classifier: Environment :: MacOS X
Classifier: Environment :: Win32 (MS Windows)
Classifier: Intended Audience :: Science/Research
Classifier: Intended Audience :: Developers
Classifier: License :: OSI Approved :: GNU Affero General Public License v3 or later (AGPLv3+)
Classifier: Operating System :: OS Independent
Classifier: Programming Language :: Python :: Implementation :: CPython
Classifier: Programming Language :: Python :: 3.5
Classifier: Programming Language :: Python :: 3.6
Classifier: Programming Language :: Python :: 3 :: Only
Classifier: Topic :: Scientific/Engineering :: Information Analysis
Classifier: Topic :: Software Development :: Quality Assurance
Classifier: Topic :: Text Processing :: Linguistic
License-File: LICENSE
Requires-Dist: coala
Requires-Dist: HTTPolice (~=0.5.2)
Requires-Dist: aenum (~=2.0.8)
Requires-Dist: apertium-lint (~=0.29)
Requires-Dist: autoflake (~=0.7)
Requires-Dist: autopep8 (~=1.2)
Requires-Dist: bandit (<1.6.3,~=1.2)
Requires-Dist: bashate (~=0.5.1)
Requires-Dist: cmakelint (~=1.3)
Requires-Dist: cppclean (~=0.12.0)
Requires-Dist: cpplint (~=1.3)
Requires-Dist: dennis (~=0.9)
Requires-Dist: docutils-ast-writer (~=0.1.2)
Requires-Dist: eradicate (~=0.1.6)
Requires-Dist: git-url-parse (~=1.1)
Requires-Dist: guess-language-spirit (~=0.5.2)
Requires-Dist: html-linter (~=0.4.0)
Requires-Dist: isort (~=4.2)
Requires-Dist: libclang-py3 (~=3.4.0)
Requires-Dist: memento-client (~=0.6.1)
Requires-Dist: munkres (~=1.1.2)
Requires-Dist: mypy (==0.590)
Requires-Dist: nbformat (~=4.1)
Requires-Dist: nltk (~=3.2)
Requires-Dist: proselint (~=0.7.0)
Requires-Dist: pycodestyle (~=2.2)
Requires-Dist: pydocstyle (~=2.0)
Requires-Dist: pyflakes (~=2.0.0)
Requires-Dist: pylint (~=1.7.2)
Requires-Dist: pyroma (~=2.2.0)
Requires-Dist: pyyaml (~=3.12)
Requires-Dist: radon (==1.4.0)
Requires-Dist: restructuredtext-lint (~=1.0)
Requires-Dist: rstcheck (~=3.1)
Requires-Dist: safety (~=1.8.2)
Requires-Dist: scspell3k (~=2.0)
Requires-Dist: sqlparse (~=0.2.4)
Requires-Dist: vim-vint (!=0.3.19,~=0.3.12)
Requires-Dist: vulture (~=0.25.0)
Requires-Dist: yamllint (~=1.12.0)
Requires-Dist: yapf (>=0.21.0<0.27.0)
Requires-Dist: lark
Provides-Extra: alldeps
Requires-Dist: HTTPolice (~=0.5.2) ; extra == 'alldeps'
Requires-Dist: aenum (~=2.0.8) ; extra == 'alldeps'
Requires-Dist: apertium-lint (~=0.29) ; extra == 'alldeps'
Requires-Dist: autoflake (~=0.7) ; extra == 'alldeps'
Requires-Dist: autopep8 (~=1.2) ; extra == 'alldeps'
Requires-Dist: bandit (<1.6.3,~=1.2) ; extra == 'alldeps'
Requires-Dist: bashate (~=0.5.1) ; extra == 'alldeps'
Requires-Dist: cmakelint (~=1.3) ; extra == 'alldeps'
Requires-Dist: cppclean (~=0.12.0) ; extra == 'alldeps'
Requires-Dist: cpplint (~=1.3) ; extra == 'alldeps'
Requires-Dist: dennis (~=0.9) ; extra == 'alldeps'
Requires-Dist: docutils-ast-writer (~=0.1.2) ; extra == 'alldeps'
Requires-Dist: eradicate (~=0.1.6) ; extra == 'alldeps'
Requires-Dist: git-url-parse (~=1.1) ; extra == 'alldeps'
Requires-Dist: guess-language-spirit (~=0.5.2) ; extra == 'alldeps'
Requires-Dist: html-linter (~=0.4.0) ; extra == 'alldeps'
Requires-Dist: isort (~=4.2) ; extra == 'alldeps'
Requires-Dist: language-check (~=1.0) ; extra == 'alldeps'
Requires-Dist: libclang-py3 (~=3.4.0) ; extra == 'alldeps'
Requires-Dist: lxml (<4.4.0,>=1.0) ; extra == 'alldeps'
Requires-Dist: memento-client (~=0.6.1) ; extra == 'alldeps'
Requires-Dist: munkres (~=1.1.2) ; extra == 'alldeps'
Requires-Dist: mypy (==0.590) ; extra == 'alldeps'
Requires-Dist: nbformat (~=4.1) ; extra == 'alldeps'
Requires-Dist: nltk (~=3.2) ; extra == 'alldeps'
Requires-Dist: proselint (~=0.7.0) ; extra == 'alldeps'
Requires-Dist: pycodestyle (~=2.2) ; extra == 'alldeps'
Requires-Dist: pydocstyle (~=2.0) ; extra == 'alldeps'
Requires-Dist: pyflakes (~=2.0.0) ; extra == 'alldeps'
Requires-Dist: pylint (~=1.7.2) ; extra == 'alldeps'
Requires-Dist: pyroma (~=2.2.0) ; extra == 'alldeps'
Requires-Dist: pyyaml (~=3.12) ; extra == 'alldeps'
Requires-Dist: radon (==1.4.0) ; extra == 'alldeps'
Requires-Dist: restructuredtext-lint (~=1.0) ; extra == 'alldeps'
Requires-Dist: rstcheck (~=3.1) ; extra == 'alldeps'
Requires-Dist: safety (~=1.8.2) ; extra == 'alldeps'
Requires-Dist: scspell3k (~=2.0) ; extra == 'alldeps'
Requires-Dist: sqlparse (~=0.2.4) ; extra == 'alldeps'
Requires-Dist: vim-vint (!=0.3.19,~=0.3.12) ; extra == 'alldeps'
Requires-Dist: vulture (~=0.25.0) ; extra == 'alldeps'
Requires-Dist: yamllint (~=1.12.0) ; extra == 'alldeps'
Requires-Dist: yapf (>=0.21.0<0.27.0) ; extra == 'alldeps'
Requires-Dist: lark ; extra == 'alldeps'
